setup.py
src/winnow/__init__.py
src/winnow/constants.py
src/winnow/exceptions.py
src/winnow/inline.py
src/winnow/interface.py
src/winnow/operations.py
src/winnow/options.py
src/winnow/utils.py
src/winnow/validation.py
src/winnow.egg-info/PKG-INFO
src/winnow.egg-info/SOURCES.txt
src/winnow.egg-info/dependency_links.txt
src/winnow.egg-info/not-zip-safe
src/winnow.egg-info/requires.txt
src/winnow.egg-info/top_level.txt
src/winnow/keys/__init__.py
src/winnow/keys/key_matching.py
src/winnow/models/__init__.py
src/winnow/models/_context_sieve.py
src/winnow/models/_product_flow.py
src/winnow/models/base.py
src/winnow/models/fileset.py
src/winnow/models/finish.py
src/winnow/models/licence.py
src/winnow/models/material.py
src/winnow/models/namespace.py
src/winnow/models/process.py
src/winnow/models/product.py
src/winnow/models/quantified_configuration.py
src/winnow/pipeline/__init__.py
src/winnow/pipeline/flow.py
src/winnow/tests/__init__.py
src/winnow/tests/base_tests.py
src/winnow/tests/boolean_tests.py
src/winnow/tests/db.py
src/winnow/tests/flow_tests.py
src/winnow/tests/key_tests.py
src/winnow/tests/manufacturing_spec_tests.py
src/winnow/tests/nested_options_tests.py
src/winnow/tests/null_option_tests.py
src/winnow/tests/numeric_tests.py
src/winnow/tests/option_tests.py
src/winnow/tests/reference_scope_tests.py
src/winnow/tests/taxonomy_tests.py
src/winnow/tests/unexpand_tests.py
src/winnow/values/__init__.py
src/winnow/values/base_values.py
src/winnow/values/boolean_values.py
src/winnow/values/numeric_values.py
src/winnow/values/option_values.py